altbc_analyzer/__init__.py
altbc_analyzer/altbc_analyzer.py
altbc_analyzer/neighbor_list.py
altbc_analyzer-0.1.0.dist-info/LICENSE
altbc_analyzer-0.1.0.dist-info/METADATA
altbc_analyzer-0.1.0.dist-info/WHEEL
altbc_analyzer-0.1.0.dist-info/top_level.txt
altbc_analyzer-0.1.0.dist-info/RECORD
